river_print/__init__.py
river_print/main.py
river_print/separator.py
river_print-0.1.6.dist-info/METADATA
river_print-0.1.6.dist-info/WHEEL
river_print-0.1.6.dist-info/licenses/LICENSE
river_print-0.1.6.dist-info/RECORD
